spyci/__init__.py
spyci/cli.py
spyci/spyci.py
spyci-1.0.2.dist-info/AUTHORS.rst
spyci-1.0.2.dist-info/LICENSE
spyci-1.0.2.dist-info/METADATA
spyci-1.0.2.dist-info/WHEEL
spyci-1.0.2.dist-info/entry_points.txt
spyci-1.0.2.dist-info/top_level.txt
spyci-1.0.2.dist-info/RECORD
