Metadata-Version: 2.1
Name: spyci
Version: 1.0.2
Summary: Spice Raw Parser
Home-page: https://github.com/gmagno/spyci
Author: Gonçalo Magno
Author-email: goncalo@gmagno.dev
License: MIT license
Keywords: spyci
Platform: UNKNOWN
Classifier: Development Status :: 2 - Pre-Alpha
Classifier: Intended Audience :: Developers
Classifier: License :: OSI Approved :: MIT License
Classifier: Natural Language :: English
Classifier: Programming Language :: Python :: 3
Classifier: Programming Language :: Python :: 3.5
Classifier: Programming Language :: Python :: 3.6
Classifier: Programming Language :: Python :: 3.7
Classifier: Programming Language :: Python :: 3.8
Requires-Python: >=3.5
Requires-Dist: matplotlib
Requires-Dist: numpy
Requires-Dist: tabulate
